CONTRIBUTING.md
LICENSE
README.md
SECURITY.md
pyproject.toml
docs/developer.md
docs/index.md
dsversioner/Dataset.py
dsversioner/DatasetMetadata.py
dsversioner/DatasetRecordData.py
dsversioner/DatasetVersion.py
dsversioner/Exceptions.py
dsversioner/FileSystemStorage.py
dsversioner/ObjectDataset.py
dsversioner/ObjectDatasetFileSystemStorage.py
dsversioner/ObjectDatasetMetadata.py
dsversioner/ObjectDatasetRecordData.py
dsversioner/ObjectDatasetStorage.py
dsversioner/ObjectDatasetVersion.py
dsversioner/Serializable.py
dsversioner/Storage.py
dsversioner/__init__.py
dsversioner-0.9.5.dist-info/METADATA
dsversioner-0.9.5.dist-info/WHEEL
dsversioner-0.9.5.dist-info/licenses/LICENSE
dsversioner-0.9.5.dist-info/RECORD
