Metadata-Version: 2.1
Name: dsversioner
Version: 0.9.5
Summary: Flexible and extensible dataset versioning.
Author-email: Maxim Dernovoi <author@example.com>
License: MIT License
License-File: LICENSE
Classifier: License :: OSI Approved :: MIT License
Classifier: Operating System :: OS Independent
Classifier: Programming Language :: Python :: 3
Requires-Python: >=3.8
Requires-Dist: pandas==2.0.1
Requires-Dist: pyarrow==12.0.0
